dirdog.py
dirdog-0.0.2.dist-info/LICENSE
dirdog-0.0.2.dist-info/METADATA
dirdog-0.0.2.dist-info/WHEEL
dirdog-0.0.2.dist-info/top_level.txt
dirdog-0.0.2.dist-info/RECORD
