Metadata-Version: 2.1
Name: dirdog
Version: 0.0.2
Summary: Simplest Watchdog for a given directory
Author-email: Daniel Ewert <ewert.daniel@gmail.com>
Classifier: Programming Language :: Python :: 3
Classifier: License :: OSI Approved :: MIT License
Classifier: Operating System :: OS Independent
Requires-Python: >=3.10
License-File: LICENSE
